aliyunsdktingwu/__init__.py
aliyunsdktingwu/request/__init__.py
aliyunsdktingwu/request/v20230930/CreateTaskRequest.py
aliyunsdktingwu/request/v20230930/CreateTranscriptionPhrasesRequest.py
aliyunsdktingwu/request/v20230930/DeleteTranscriptionPhrasesRequest.py
aliyunsdktingwu/request/v20230930/GetTaskInfoRequest.py
aliyunsdktingwu/request/v20230930/GetTranscriptionPhrasesRequest.py
aliyunsdktingwu/request/v20230930/ListTranscriptionPhrasesRequest.py
aliyunsdktingwu/request/v20230930/UpdateTranscriptionPhrasesRequest.py
aliyunsdktingwu/request/v20230930/__init__.py
aliyun_python_sdk_tingwu-1.0.7.dist-info/LICENSE
aliyun_python_sdk_tingwu-1.0.7.dist-info/METADATA
aliyun_python_sdk_tingwu-1.0.7.dist-info/WHEEL
aliyun_python_sdk_tingwu-1.0.7.dist-info/top_level.txt
aliyun_python_sdk_tingwu-1.0.7.dist-info/RECORD
